dotmod.py
dotmod-0.0.3.dist-info/DESCRIPTION.rst
dotmod-0.0.3.dist-info/metadata.json
dotmod-0.0.3.dist-info/WHEEL
dotmod-0.0.3.dist-info/top_level.txt
dotmod-0.0.3.dist-info/METADATA
dotmod-0.0.3.dist-info/RECORD
