Metadata-Version: 2.0
Name: dotmod
Version: 0.0.3
Summary: Import Python packages from folders with dotted names
Home-page: https://github.com/sciyoshi/dotmod/
Author: Samuel Cormier-Iijima
Author-email: sciyoshi@gmail.com
License: MIT
Keywords: namespace modules dotmod imports hooks importhook packages
Platform: UNKNOWN
Classifier: Development Status :: 3 - Alpha
Classifier: Intended Audience :: Developers
Classifier: License :: OSI Approved :: MIT License
Classifier: Programming Language :: Python :: 2
Classifier: Programming Language :: Python :: 2.6
Classifier: Programming Language :: Python :: 2.7
Classifier: Programming Language :: Python :: 3
Classifier: Programming Language :: Python :: 3.3
Classifier: Programming Language :: Python :: 3.4
Requires-Dist: six (>=1.8.0)
